onegov.feriennet-1.6.16-py3.6-nspkg.pth
onegov/feriennet/.gitignore
onegov/feriennet/__init__.py
onegov/feriennet/app.py
onegov/feriennet/cli.py
onegov/feriennet/const.py
onegov/feriennet/converters.py
onegov/feriennet/custom.py
onegov/feriennet/homepage_widgets.py
onegov/feriennet/initial_content.py
onegov/feriennet/layout.py
onegov/feriennet/path.py
onegov/feriennet/policy.py
onegov/feriennet/redirects.py
onegov/feriennet/request.py
onegov/feriennet/security.py
onegov/feriennet/sponsors.py
onegov/feriennet/translations.py
onegov/feriennet/upgrade.py
onegov/feriennet/utils.py
onegov/feriennet/assets/js/click-to-load.js
onegov/feriennet/assets/js/print.js
onegov/feriennet/assets/js/printthis.js
onegov/feriennet/assets/js/reloadfrom.js
onegov/feriennet/assets/js/tracking.js
onegov/feriennet/collections/__init__.py
onegov/feriennet/collections/activity.py
onegov/feriennet/collections/billing.py
onegov/feriennet/collections/match.py
onegov/feriennet/collections/notification_template.py
onegov/feriennet/collections/occasion_attendees.py
onegov/feriennet/content/de.yaml
onegov/feriennet/content/fr.yaml
onegov/feriennet/content/images/1zr3wnstnvy-aaron-burden.jpg
onegov/feriennet/content/images/hn5ytnkwuxw-markus-spiske.jpg
onegov/feriennet/content/images/rx2vjcjqtxi-elissa-algora.jpg
onegov/feriennet/content/images/sahbl2upxco-ashton-bingham.jpg
onegov/feriennet/exports/__init__.py
onegov/feriennet/exports/base.py
onegov/feriennet/exports/booking.py
onegov/feriennet/exports/const.py
onegov/feriennet/exports/invoiceitem.py
onegov/feriennet/exports/occasion.py
onegov/feriennet/exports/user.py
onegov/feriennet/forms/__init__.py
onegov/feriennet/forms/activity.py
onegov/feriennet/forms/attendee.py
onegov/feriennet/forms/bank_statement.py
onegov/feriennet/forms/billing.py
onegov/feriennet/forms/donation.py
onegov/feriennet/forms/match.py
onegov/feriennet/forms/notification_template.py
onegov/feriennet/forms/occasion.py
onegov/feriennet/forms/occasion_need.py
onegov.feriennet-1.6.16.dist-info/METADATA
onegov.feriennet-1.6.16.dist-info/WHEEL
onegov.feriennet-1.6.16.dist-info/entry_points.txt
onegov.feriennet-1.6.16.dist-info/namespace_packages.txt
onegov.feriennet-1.6.16.dist-info/top_level.txt
onegov.feriennet-1.6.16.dist-info/RECORD
