Metadata-Version: 2.1
Name: onegov.feriennet
Version: 1.6.16
Summary: Ferienpass Management for Pro Juventute
Home-page: http://github.com/OneGov/onegov.feriennet
Author: Seantis GmbH
Author-email: info@seantis.ch
License: GPLv2
Platform: any
Classifier: Intended Audience :: Developers
Classifier: Programming Language :: Python :: 3 :: Only
Classifier: Programming Language :: Python :: 3.6
Classifier: Programming Language :: Python :: 3.7
Classifier: Topic :: Software Development :: Libraries :: Python Modules
Classifier: License :: OSI Approved :: GNU General Public License v2 (GPLv2)
Requires-Python: >=3.6
Requires-Dist: faker
Requires-Dist: icalendar
Requires-Dist: onegov.activity
Requires-Dist: onegov.core (>=0.70.5)
Requires-Dist: onegov.org (>=0.20.0)
Provides-Extra: test
Requires-Dist: coverage ; extra == 'test'
Requires-Dist: faker ; extra == 'test'
Requires-Dist: freezegun ; extra == 'test'
Requires-Dist: onegov-testing ; extra == 'test'
Requires-Dist: pytest ; extra == 'test'
Requires-Dist: pytest-localserver ; extra == 'test'
Requires-Dist: pyquery ; extra == 'test'
Requires-Dist: requests-mock ; extra == 'test'
Requires-Dist: ulid ; extra == 'test'
